{
  "_id": "BG1.21",
  "chapter": 1,
  "verse": 21,
  "slok": "अर्जुन उवाच |\nसेनयोरुभयोर्मध्ये रथं स्थापय मेऽच्युत ||१-२१||",
  "transliteration": "hṛṣīkeśaṃ tadā vākyamidamāha mahīpate .\narjuna uvāca .\nsenayorubhayormadhye rathaṃ sthāpaya me.acyuta ||1-21||",
  "siva": {
    "author": "Swami Sivananda",
    "et": "1.21 Arjuna said  In the middle between the two armies, place my chariot,\nO krishna, so that I may behold those who stand here desirous to fight,\nand know with whom I must fight, when the battle is about to commence.",
    "ec": "1.21 -- 1.22 सेनयोः of the armies? उभयोः of both? मध्ये in the middle? रथम् car? स्थापय place? मे my? अच्युत O Achyuta (O changeless? Krishna)? यावत् while? एतान् these? निरीक्षे behold? अहम् I? योद्धुकामान् desirous to fight? अवस्थितान् standing? कैः with whom? मया by me? सह together? योद्धव्यम् must be fought? अस्मिन् in this? रणसमुद्यमे eve of battle.No Commentary."
  }
}