{
  "_id": "BG3.44",
  "chapter": 3,
  "verse": 44,
  "slok": "ॐ तत्सदिति श्रीमद्भगवद्गीतासूपनिषत्सु\nब्रह्मविद्यायां योगशास्त्रे श्रीकृष्णार्जुनसंवादे\nकर्मयोगो नाम तृतीयोऽध्यायः ||३||",
  "transliteration": "OM tatsaditi śrīmadbhagavadgītāsūpaniṣatsu brahmavidyāyāṃ yogaśāstre śrīkṛṣṇārjunasaṃvāde karmayogo nāma tṛtīyo.adhyāyaḥ ||3-44||",
  "siva": {
    "author": "Swami Sivananda",
    "et": "Swami Sivananda did not comment on this sloka",
    "ec": "Swami Sivananda did not comment on this sloka"
  }
}